README.md
setup.py
swws/__init__.py
swws.egg-info/PKG-INFO
swws.egg-info/SOURCES.txt
swws.egg-info/dependency_links.txt
swws.egg-info/requires.txt
swws.egg-info/top_level.txt