Metadata-Version: 2.1
Name: swws
Version: 0.1
Summary: Package Description
Home-page: UNKNOWN
Author: SALAD37
Author-email: nonemovo@gmail.com
License: UNKNOWN
Project-URL: Bug Tracker, https://bugs.example.com/HelloWorld/
Project-URL: Documentation, https://docs.example.com/HelloWorld/
Project-URL: Source Code, https://code.example.com/HelloWorld/
Platform: UNKNOWN
